Workbook

Sheet Monthly Data
A1: 📊 MONTHLY PERFORMANCE TRACKER — 2024 Annual Records
A2: Track monthly Sales Revenue, Units Sold, New Customers, Expenses, and Profit — all KPIs calculated automatically.
A3: Month | B3: Sales Revenue ($) | C3: Units Sold | D3: New Customers | E3: Expenses ($) | F3: Gross Profit ($) | G3: Profit Margin (%) | H3: MoM Growth (%) | I3: vs Avg (%)
A4: January | B4: 142500 | C4: 285 | D4: 42 | E4: 98400 | F4: =B4-E4 -> 44100 | G4: =IF(B4>0,F4/B4,0) -> 0.30947368 | H4: — | I4: =(B4-AVERAGE($B$4:$B$15))/AVERAGE($B$4:$B$15) -> -0.26832399
A5: February | B5: 128300 | C5: 257 | D5: 38 | E5: 91200 | F5: =B5-E5 -> 37100 | G5: =IF(B5>0,F5/B5,0) -> 0.28916602 | H5: =(B5-B4)/B4 -> -0.099649123 | I5: =(B5-AVERAGE($B$4:$B$15))/AVERAGE($B$4:$B$15) -> -0.34123486
A6: March | B6: 155800 | C6: 312 | D6: 51 | E6: 104600 | F6: =B6-E6 -> 51200 | G6: =IF(B6>0,F6/B6,0) -> 0.32862644 | H6: =(B6-B5)/B5 -> 0.21434139 | I6: =(B6-AVERAGE($B$4:$B$15))/AVERAGE($B$4:$B$15) -> -0.20003423
A7: April | B7: 163200 | C7: 326 | D7: 56 | E7: 109800 | F7: =B7-E7 -> 53400 | G7: =IF(B7>0,F7/B7,0) -> 0.32720588 | H7: =(B7-B6)/B6 -> 0.047496791 | I7: =(B7-AVERAGE($B$4:$B$15))/AVERAGE($B$4:$B$15) -> -0.16203842
A8: May | B8: 179400 | C8: 359 | D8: 63 | E8: 118500 | F8: =B8-E8 -> 60900 | G8: =IF(B8>0,F8/B8,0) -> 0.33946488 | H8: =(B8-B7)/B7 -> 0.099264706 | I8: =(B8-AVERAGE($B$4:$B$15))/AVERAGE($B$4:$B$15) -> -0.078858414
A9: June | B9: 195600 | C9: 391 | D9: 71 | E9: 127300 | F9: =B9-E9 -> 68300 | G9: =IF(B9>0,F9/B9,0) -> 0.349182 | H9: =(B9-B8)/B8 -> 0.090301003 | I9: =(B9-AVERAGE($B$4:$B$15))/AVERAGE($B$4:$B$15) -> 0.0043215951
A10: July | B10: 188300 | C10: 377 | D10: 68 | E10: 124100 | F10: =B10-E10 -> 64200 | G10: =IF(B10>0,F10/B10,0) -> 0.3409453 | H10: =(B10-B9)/B9 -> -0.037321063 | I10: =(B10-AVERAGE($B$4:$B$15))/AVERAGE($B$4:$B$15) -> -0.033160755
A11: August | B11: 201500 | C11: 403 | D11: 74 | E11: 131200 | F11: =B11-E11 -> 70300 | G11: =IF(B11>0,F11/B11,0) -> 0.34888337 | H11: =(B11-B10)/B10 -> 0.070100903 | I11: =(B11-AVERAGE($B$4:$B$15))/AVERAGE($B$4:$B$15) -> 0.034615549
A12: September | B12: 217800 | C12: 436 | D12: 82 | E12: 138900 | F12: =B12-E12 -> 78900 | G12: =IF(B12>0,F12/B12,0) -> 0.36225895 | H12: =(B12-B11)/B11 -> 0.0808933 | I12: =(B12-AVERAGE($B$4:$B$15))/AVERAGE($B$4:$B$15) -> 0.11830902
A13: October | B13: 234600 | C13: 469 | D13: 89 | E13: 146700 | F13: =B13-E13 -> 87900 | G13: =IF(B13>0,F13/B13,0) -> 0.37468031 | H13: =(B13-B12)/B12 -> 0.077134986 | I13: =(B13-AVERAGE($B$4:$B$15))/AVERAGE($B$4:$B$15) -> 0.20456977
A14: November | B14: 251200 | C14: 502 | D14: 97 | E14: 154800 | F14: =B14-E14 -> 96400 | G14: =IF(B14>0,F14/B14,0) -> 0.38375796 | H14: =(B14-B13)/B13 -> 0.070758738 | I14: =(B14-AVERAGE($B$4:$B$15))/AVERAGE($B$4:$B$15) -> 0.2898036
A15: December | B15: 278900 | C15: 558 | D15: 112 | E15: 167300 | F15: =B15-E15 -> 111600 | G15: =IF(B15>0,F15/B15,0) -> 0.40014342 | H15: =(B15-B14)/B14 -> 0.1102707 | I15: =(B15-AVERAGE($B$4:$B$15))/AVERAGE($B$4:$B$15) -> 0.43203115
A16: FULL YEAR | B16: =SUM(B4:B15) -> 2337100 | C16: =SUM(C4:C15) -> 4675 | D16: =SUM(D4:D15) -> 843 | E16: =SUM(E4:E15) -> 1512800 | F16: =SUM(F4:F15) -> 824300 | G16: =F16/B16 -> 0.35270207 | H16: =(B15-B4)/B4 -> 0.95719298 | I16: —
A17: MONTHLY AVG | B17: =AVERAGE(B4:B15) -> 194758.33 | C17: =AVERAGE(C4:C15) -> 389.58333 | D17: =AVERAGE(D4:D15) -> 70.25 | E17: =AVERAGE(E4:E15) -> 126066.67 | F17: =AVERAGE(F4:F15) -> 68691.667 | G17: =AVERAGE(G4:G15) -> 0.34614902 | H17: =AVERAGE(H5:H15) -> 0.065781121 | I17: —

Sheet KPI Dashboard
A1: 🏆 KEY PERFORMANCE INDICATORS — 2024 ANNUAL DASHBOARD
A3: 💰 Total Revenue | D3: 📦 Units Sold | G3: 👥 New Customers | J3: 📈 Avg Profit Margin
A4: ='Monthly Data'!B16 -> 2337100 | D4: ='Monthly Data'!C16 -> 4675 | G4: ='Monthly Data'!D16 -> 843 | J4: ='Monthly Data'!G17 -> 0.34614902
A8: Metric | B8: Best Month | C8: Best Value | D8: Worst Month | E8: Worst Value | F8: Full-Year Total | G8: Monthly Avg
A9: Sales Revenue ($) | B9: =INDEX('Monthly Data'!$A$4:$A$15,MATCH(MAX('Monthly Data'!$B$4:$B$15),'Monthly Data'!$B$4:$B$15,0)) -> December | C9: =MAX('Monthly Data'!B4:B15) -> 278900 | D9: =INDEX('Monthly Data'!$A$4:$A$15,MATCH(MIN('Monthly Data'!$B$4:$B$15),'Monthly Data'!$B$4:$B$15,0)) -> February | E9: =MIN('Monthly Data'!B4:B15) -> 128300 | F9: ='Monthly Data'!B16 -> 2337100 | G9: ='Monthly Data'!B17 -> 194758.33
A10: Units Sold | B10: =INDEX('Monthly Data'!$A$4:$A$15,MATCH(MAX('Monthly Data'!$C$4:$C$15),'Monthly Data'!$C$4:$C$15,0)) -> December | C10: =MAX('Monthly Data'!C4:C15) -> 558 | D10: =INDEX('Monthly Data'!$A$4:$A$15,MATCH(MIN('Monthly Data'!$C$4:$C$15),'Monthly Data'!$C$4:$C$15,0)) -> February | E10: =MIN('Monthly Data'!C4:C15) -> 257 | F10: ='Monthly Data'!C16 -> 4675 | G10: ='Monthly Data'!C17 -> 389.58333
A11: New Customers | B11: =INDEX('Monthly Data'!$A$4:$A$15,MATCH(MAX('Monthly Data'!$D$4:$D$15),'Monthly Data'!$D$4:$D$15,0)) -> December | C11: =MAX('Monthly Data'!D4:D15) -> 112 | D11: =INDEX('Monthly Data'!$A$4:$A$15,MATCH(MIN('Monthly Data'!$D$4:$D$15),'Monthly Data'!$D$4:$D$15,0)) -> February | E11: =MIN('Monthly Data'!D4:D15) -> 38 | F11: ='Monthly Data'!D16 -> 843 | G11: ='Monthly Data'!D17 -> 70.25
A12: Gross Profit ($) | B12: =INDEX('Monthly Data'!$A$4:$A$15,MATCH(MAX('Monthly Data'!$F$4:$F$15),'Monthly Data'!$F$4:$F$15,0)) -> December | C12: =MAX('Monthly Data'!F4:F15) -> 111600 | D12: =INDEX('Monthly Data'!$A$4:$A$15,MATCH(MIN('Monthly Data'!$F$4:$F$15),'Monthly Data'!$F$4:$F$15,0)) -> February | E12: =MIN('Monthly Data'!F4:F15) -> 37100 | F12: ='Monthly Data'!F16 -> 824300 | G12: ='Monthly Data'!F17 -> 68691.667
A13: Profit Margin (%) | B13: =INDEX('Monthly Data'!$A$4:$A$15,MATCH(MAX('Monthly Data'!$G$4:$G$15),'Monthly Data'!$G$4:$G$15,0)) -> December | C13: =MAX('Monthly Data'!G4:G15) -> 0.40014342 | D13: =INDEX('Monthly Data'!$A$4:$A$15,MATCH(MIN('Monthly Data'!$G$4:$G$15),'Monthly Data'!$G$4:$G$15,0)) -> February | E13: =MIN('Monthly Data'!G4:G15) -> 0.28916602 | F13: ='Monthly Data'!G16 -> 0.35270207 | G13: ='Monthly Data'!G17 -> 0.34614902

Sheet Quarterly Rollup
A1: 📅 QUARTERLY PERFORMANCE ROLLUP — 2024
A2: Quarter | B2: Revenue ($) | C2: Units Sold | D2: New Customers | E2: Expenses ($) | F2: Gross Profit ($) | G2: Avg Margin (%) | H2: QoQ Growth (%)
A3: Q1 (Jan–Mar) | B3: =SUMPRODUCT(('Monthly Data'!B4:'Monthly Data'!B6)) -> 426600 | C3: =SUMPRODUCT(('Monthly Data'!C4:'Monthly Data'!C6)) -> 854 | D3: =SUMPRODUCT(('Monthly Data'!D4:'Monthly Data'!D6)) -> 131 | E3: =SUMPRODUCT(('Monthly Data'!E4:'Monthly Data'!E6)) -> 294200 | F3: =B3-E3 -> 132400 | G3: =F3/B3 -> 0.31036099 | H3: —
A4: Q2 (Apr–Jun) | B4: =SUMPRODUCT(('Monthly Data'!B7:'Monthly Data'!B9)) -> 538200 | C4: =SUMPRODUCT(('Monthly Data'!C7:'Monthly Data'!C9)) -> 1076 | D4: =SUMPRODUCT(('Monthly Data'!D7:'Monthly Data'!D9)) -> 190 | E4: =SUMPRODUCT(('Monthly Data'!E7:'Monthly Data'!E9)) -> 355600 | F4: =B4-E4 -> 182600 | G4: =F4/B4 -> 0.33927908 | H4: =(B4-B3)/B3 -> 0.26160338
A5: Q3 (Jul–Sep) | B5: =SUMPRODUCT(('Monthly Data'!B10:'Monthly Data'!B12)) -> 607600 | C5: =SUMPRODUCT(('Monthly Data'!C10:'Monthly Data'!C12)) -> 1216 | D5: =SUMPRODUCT(('Monthly Data'!D10:'Monthly Data'!D12)) -> 224 | E5: =SUMPRODUCT(('Monthly Data'!E10:'Monthly Data'!E12)) -> 394200 | F5: =B5-E5 -> 213400 | G5: =F5/B5 -> 0.35121791 | H5: =(B5-B4)/B4 -> 0.12894835
A6: Q4 (Oct–Dec) | B6: =SUMPRODUCT(('Monthly Data'!B13:'Monthly Data'!B15)) -> 764700 | C6: =SUMPRODUCT(('Monthly Data'!C13:'Monthly Data'!C15)) -> 1529 | D6: =SUMPRODUCT(('Monthly Data'!D13:'Monthly Data'!D15)) -> 298 | E6: =SUMPRODUCT(('Monthly Data'!E13:'Monthly Data'!E15)) -> 468800 | F6: =B6-E6 -> 295900 | G6: =F6/B6 -> 0.38694913 | H6: =(B6-B5)/B5 -> 0.25855826
A7: FULL YEAR | B7: ='Monthly Data'!B16 -> 2337100 | C7: ='Monthly Data'!C16 -> 4675 | D7: ='Monthly Data'!D16 -> 843 | E7: ='Monthly Data'!E16 -> 1512800 | F7: ='Monthly Data'!F16 -> 824300 | G7: ='Monthly Data'!G16 -> 0.35270207 | H7: =(B3+B4+B5+B6-4*B3)/(3*B3) -> 0.49281138

Sheet Trend Analysis
A1: 📉 TREND ANALYSIS — Growth Rates, Highs & Lows, Statistical Summary
A3: REVENUE ANALYTICS
A4: Annual Total | B4: ='Monthly Data'!B16 -> 2337100
A5: Monthly Average | B5: ='Monthly Data'!B17 -> 194758.33
A6: Peak Month Revenue | B6: =MAX('Monthly Data'!B4:B15) -> 278900
A7: Lowest Month Revenue | B7: =MIN('Monthly Data'!B4:B15) -> 128300
A8: Revenue Range | B8: =MAX('Monthly Data'!B4:B15)-MIN('Monthly Data'!B4:B15) -> 150600
A9: Full-Year Growth | B9: =(MAX('Monthly Data'!B4:B15)-MIN('Monthly Data'!B4:B15))/MIN('Monthly Data'!B4:B15) -> 1.1738114
A10: Best MoM Growth | B10: =MAX('Monthly Data'!H5:H15) -> 0.21434139
A12: PROFITABILITY
A13: Total Gross Profit | B13: ='Monthly Data'!F16 -> 824300
A14: Avg Monthly Profit | B14: ='Monthly Data'!F17 -> 68691.667
A15: Best Margin Month | B15: =MAX('Monthly Data'!G4:G15) -> 0.40014342
A16: Weakest Margin Month | B16: =MIN('Monthly Data'!G4:G15) -> 0.28916602
A17: Avg Profit Margin | B17: ='Monthly Data'!G17 -> 0.34614902
A19: CUSTOMERS & VOLUME
A20: Total New Customers | B20: ='Monthly Data'!D16 -> 843
A21: Avg New Cust/Month | B21: ='Monthly Data'!D17 -> 70.25
A22: Total Units Sold | B22: ='Monthly Data'!C16 -> 4675
A23: Avg Units/Month | B23: ='Monthly Data'!C17 -> 389.58333
A26: MONTHLY REVENUE HEATMAP (darker = higher revenue)
A27: January | B27: February | C27: March | D27: April | E27: May | F27: June | G27: July | H27: August | I27: September | J27: October | K27: November | L27: December
A28: 142500 | B28: 128300 | C28: 155800 | D28: 163200 | E28: 179400 | F28: 195600 | G28: 188300 | H28: 201500 | I28: 217800 | J28: 234600 | K28: 251200 | L28: 278900
